files/usbbl2runpara_ddrinit.bin
files/usbbl2runpara_runfipimg.bin
files/khadas-vim/u-boot.bin.usb.bl2
files/khadas-vim/u-boot.bin.usb.tpl
files/khadas-vim2/u-boot.bin.sd.bin
files/khadas-vim2/u-boot.bin.usb.bl2
files/khadas-vim2/u-boot.bin.usb.tpl
files/khadas-vim3/u-boot.bin
files/khadas-vim3/u-boot.orig.bin
files/khadas-vim3l/u-boot.bin
files/khadas-vim3l/u-boot.orig.bin
files/libretech-ac/u-boot.bin
files/libretech-ac/u-boot.bin.sd.bin
files/libretech-ac/u-boot.bin.usb.bl2
files/libretech-ac/u-boot.bin.usb.tpl
files/libretech-ac/u-boot.orig.bin
files/libretech-cc/u-boot.bin.usb.bl2
files/libretech-cc/u-boot.bin.usb.tpl
files/libretech-s905d-pc/u-boot.bin
files/libretech-s905d-pc/u-boot.bin.sd.bin
files/libretech-s905d-pc/u-boot.bin.usb.bl2
files/libretech-s905d-pc/u-boot.bin.usb.tpl
files/libretech-s905d-pc/u-boot.orig.bin
files/libretech-s912-pc/u-boot.bin
files/libretech-s912-pc/u-boot.bin.sd.bin
files/libretech-s912-pc/u-boot.bin.usb.bl2
files/libretech-s912-pc/u-boot.bin.usb.tpl
files/libretech-s912-pc/u-boot.orig.bin
files/odroid-c4/u-boot.bin
files/odroid-c4/u-boot.orig.bin
files/odroid-n2/u-boot.bin
files/odroid-n2/u-boot.orig.bin
files/p212/u-boot.bin
files/p212/u-boot.bin.sd.bin
files/p212/u-boot.bin.usb.bl2
files/p212/u-boot.bin.usb.tpl
files/p212/u-boot.orig.bin
files/q200/u-boot.bin.usb.bl2
files/q200/u-boot.bin.usb.tpl
files/s400/u-boot.bin
files/s400/u-boot.bin.sd.bin
files/s400/u-boot.bin.usb.bl2
files/s400/u-boot.bin.usb.tpl
files/s400/u-boot.orig.bin
files/sei510/u-boot.bin
files/sei510/u-boot.orig.bin
files/sei610/u-boot.bin
files/sei610/u-boot.orig.bin
files/u200/u-boot.bin
files/u200/u-boot.orig.bin
pyamlboot/__init__.py
pyamlboot/pyamlboot.py
pyamlboot-1.0.0.data/scripts/boot-g12.py
pyamlboot-1.0.0.data/scripts/boot.py
pyamlboot-1.0.0.data/scripts/runKernel.py
pyamlboot-1.0.0.data/scripts/socid.py
pyamlboot-1.0.0.dist-info/LICENSE
pyamlboot-1.0.0.dist-info/METADATA
pyamlboot-1.0.0.dist-info/WHEEL
pyamlboot-1.0.0.dist-info/top_level.txt
pyamlboot-1.0.0.dist-info/RECORD
