Metadata-Version: 2.1
Name: pyamlboot
Version: 1.0.0
Summary: Amlogic SoC USB Boot utility
Home-page: https://github.com/superna9999/pyamlboot
Author: Neil Armstrong
Author-email: superna9999@gmail.com
License: Apache 2.0
Platform: UNKNOWN
Requires-Dist: pyusb
Requires-Dist: setuptools
